{
        "products": [
              {
                  "id": 1,
                  "name": "Ryann",
                  "exp": 5,
                  "status": true,
                  "image": "https://static.bangkokpost.com/media/content/20200619/c1_1937552_200619122619.jpg"
              },
              {
                  "id": 2,
                  "name": "John",
                  "exp": 7,
                  "status": true,
                  "image": "https://static.bangkokpost.com/media/content/dcx/2021/06/04/3992275.jpg"
              },
              {
                  "id": 3,
                  "name": "Harry",
                  "exp": 3,
                  "status": true,
                  "image": "https://encrypted-tbn0.gstatic.com/images?q=tbn:ANd9GcRi_cBngAtLpNf4XrizZhJj--VsQd7TG9S1D1E_9O3ljdHmLahayIdKhbsmb9vZfsyJQ0M&usqp=CAU"
              },
              {
                  "id": 4,
                  "name": "linda",
                  "exp": 9,
                  "status": true,
                  "image": "https://encrypted-tbn0.gstatic.com/images?q=tbn:ANd9GcRna0Yn_AMMEcnVGFuHNG0-UENJAFjsGKO8RQ&usqp=CAU"
              },
              {
                  "id": 5,
                  "name": "Richel",
                  "exp": 4,
                  "status": true,
                  "image": "https://res.cloudinary.com/dk0z4ums3/image/upload/v1613385371/attached_image/ini-tanda-dan-cara-untuk-berhenti-menjadi-people-pleaser.jpg"
              },
              {
                  "id": 6,
                  "name": "Angle",
                  "exp": 2,
                  "status": true,
                  "image": "https://img.freepik.com/free-photo/lifestyle-people-emotions-casual-concept-confident-nice-smiling-asian-woman-cross-arms-chest-confident-ready-help-listening-coworkers-taking-part-conversation_1258-59335.jpg?w=2000"
              },
              {
                  "id": 7,
                  "name": "Ronny",
                  "exp": 7,
                  "status": true,
                  "image": "https://image1.masterfile.com/getImage/NjExOC0wNzEyMjM2N2VuLjAwMDAwMDAw=AOzbrc/6118-07122367en_Masterfile.jpg"
              },
              {
                  "id":8,
                  "name": "Steve",
                  "exp": 6,
                  "status": true,
                  "image": "https://us.123rf.com/450wm/szefei/szefei1511/szefei151100137/47875293-portrait-of-asian-indian-business-man-smiling-outside-modern-office-building-block-beautiful-golden-.jpg?ver=6"
              }
        ]
}